{
    "sidebar": {
        "home": "Dashboard",
        "playOnline": "Play Online",
        "challenge": "Challenge",
        "leaderboard": "Leaderboard",
        "myStats": "My Stats",
        "tournaments": "Tournaments",
        "community": "Community",
        "chatWithFriends": "Chat with Friends",
        "friendsList": "Friends List",
        "extras": "Extras",
        "shop": "Shop",
        "premiumPlans": "Premium Plans",
        "settings": "Settings",
        "login": "Login",
        "logout": "Logout",
        "upgrade": "Upgrade"
    },
    "page": {
        "shop": {
            "title": "Shop",
            "buy": "Buy",
            "filters": {
                "all": "All",
                "pucks": "Pucks",
                "strikers": "Strikers",
                "tables": "Tables"
            },
            "owned": "Owned",
            "equiped": "Equipped",
            "equip": "Equip",
            "notEnoughMoney": "You do not have enough money to buy this item."
        },
        "home": {
            "title": "Home"
        },
        "login": {
            "title": "Welcome Back !",
            "description": "Sign in to your Hockair account",
            "email": "Email",
            "password": "Password",
            "placeholder": {
                "email": "Enter your email",
                "password": "Enter your password"
            },
            "button": "Login",
            "dontHaveAccount": "Don't have an account?",
            "signupRedirect": "Sign up"
        },
        "activateAccount": {
            "title": "Account Activated!",
            "description": "Your account has been successfully activated. You can now log in and enjoy all the features of our platform."
        },
        "messageUser": {
            "chatWith": "Chat with",
            "selectContact": "Select a contact to start chatting",
            "typeMessage": "Type a message...",
            "sendMessage": "Send",
            "deleteMessage": "Delete Message",
            "cancel": "Cancel"
        },
        "profile": {
            "title": "My Profile",
            "info": {
                "title": "User Information",
                "elo": "Elo",
                "level": "Level",
                "victories": "Victories",
                "defeats": "Defeats",
                "picturePlaceholder": "Click here to add a photo",
                "pictureUpdated": "Your profile picture has been updated successfully!",
                "uploadError": "Error uploading profile picture."
            },
            "edit": {
                "title": "Edit Information",
                "username": "Username",
                "email": "Email Address",
                "currentPassword": "Current Password",
                "newPassword": "New Password",
                "confirmNewPassword": "Confirm New Password",
                "saveButton": "Save"
            },
            "errors": {
                "usernameRequired": "Username is required",
                "invalidEmail": "Invalid email address",
                "passwordTooShort": "Password must be at least 6 characters",
                "passwordMismatch": "Passwords do not match"
            },
            "updateSuccess": "Profile updated successfully!",
            "updateError": "Error updating profile"
        },
        "choixLangue": {
            "title": "Choose your language"
        },
        "friendsRequest": {
            "block": "Block",
            "message": "Message",
            "delete": "Delete",
            "level": "Level",
            "accept": "Accept",
            "decline": "Decline",
            "unknown": "Unknown",
            "messageFriendRequest": "Friend Requests",
            "searchPlaceholder": "Search for friends...",
            "friendDeletedSuccess": "Friend deleted successfully!",
            "friendDeletedError": "Error deleting friend.",
            "errorFetchingBlockedFriends": "Error fetching blocked friends.",
            "friendUnblockedSuccess": "Friend unblocked successfully!",
            "friendUnblockedError": "Error unblocking friend.",
            "friendBlockedSuccess": "Friend blocked successfully!",
            "friendBlockedError": "Error blocking friend.",
            "friendAcceptedError": "Error accepting friend request.",
            "friendAcceptedSuccess": "Friend request accepted successfully!",
            "friendRequestSentSuccess": "Friend request sent successfully!",
            "friendRequestSentError": "Error sending friend request.",
            "friendRequestAlreadySent": "Friend request already sent.",
            "errorSearchingUsers": "Error searching for users.",
            "errorFetchingRequests": "Error fetching friend requests.",
            "errorFetchingUserProfile": "Error fetching user profile.",
            "friendDeclinedError": "Error declining friend request.",
            "friendDeclinedSuccess": "Friend request declined successfully!",
            "unexpectedError": "An unexpected error occurred.",
            "errorFetchingFriends": "Error fetching friends."
        },
        "register": {
            "title": "Create an Account",
            "description": "Sign up to join AirHockey and challenge your friends!",
            "username": "Username",
            "email": "Email Address",
            "password": "Password",
            "confirmPassword": "Confirm Password",
            "placeholder": {
                "username": "Enter your username",
                "email": "Enter your email address",
                "password": "Enter your password",
                "confirmPassword": "Confirm your password"
            },
            "button": "Sign Up",
            "alreadyHaveAccount": "Already have an account?",
            "loginRedirect": "Log in"
        }
    },
    "errors": {
        "genericError": "An error occurred.",
        "serverError": "Server error. Please try again later.",
        "passwordsDoNotMatch": "Passwords do not match.",
        "weakPassword": "Password must be at least 8 characters long, include one uppercase letter, one lowercase letter, one number, and one special character.",
        "genericError": "An error occurred.",
        "serverError": "Server error. Please try again later."
    },
    "success": {
        "registerSuccess": "Account successfully created!"
    },
    "footer": {
        "left": {
            "title": "Hockair",
            "description": "The ultimate AirHockey experience. Play online, compete in tournaments, and climb the global leaderboard."
        },
        "links": {
            "home": "Home",
            "leaderboard": "Leaderboard",
            "tournaments": "Tournaments",
            "premiumPlans": "Premium Plans",
            "contactUs": "Contact Us"
        },
        "right": {
            "copyright": "© 2024 Hockair. All rights reserved."
        }
    }
}
